pypi_multidl.py
pypi_multidl-1.1.0.dist-info/entry_points.txt
pypi_multidl-1.1.0.dist-info/LICENSE
pypi_multidl-1.1.0.dist-info/WHEEL
pypi_multidl-1.1.0.dist-info/METADATA
pypi_multidl-1.1.0.dist-info/RECORD
