Metadata-Version: 2.1
Name: pypi-multidl
Version: 1.1.0
Summary: A tool to download Python packages for later offline installation on many platforms
Author-email: Rasmus Bondesson <raek@raek.se>
Classifier: License :: OSI Approved :: MIT License
Requires-Dist: packaging
Requires-Dist: requests
Project-URL: GitHub, https://github.com/raek/pypi-multidl/
